chembl_gen_check/__init__.py
chembl_gen_check/create_mol_filters.py
chembl_gen_check/lacan.py
chembl_gen_check/ring_systems.py
chembl_gen_check/data/chembl_lacan.pkl
chembl_gen_check/data/chembl_ring_system.bloom
chembl_gen_check/data/chembl_scaffold.bloom
chembl_gen_check/data/chembl_skeleton.bloom
chembl_gen_check-0.1.1.dist-info/METADATA
chembl_gen_check-0.1.1.dist-info/WHEEL
chembl_gen_check-0.1.1.dist-info/entry_points.txt
chembl_gen_check-0.1.1.dist-info/licenses/LICENSE
chembl_gen_check-0.1.1.dist-info/RECORD
