Metadata-Version: 2.4
Name: chembl_gen_check
Version: 0.1.1
Summary: Simple package that performs basic molecular structural sanity checks
License-File: LICENSE
Requires-Python: >=3.10
Requires-Dist: molbloom>=2.2.1
Requires-Dist: rdkit>=2022.3.3
Provides-Extra: create
Requires-Dist: chembl-downloader; extra == 'create'
Requires-Dist: tqdm; extra == 'create'
